[{"title":"Je trouve l'identité d'inconnus dans la rue avec l'IA.","link":"https://www.youtube.com/watch?v=Vvqa5bxDU9Y","pubDate":"2022-08-10T10:01:13.000Z","author":"Defend Intelligence","id":"yt:video:Vvqa5bxDU9Y","isoDate":"2022-08-10T10:01:13.000Z"},{"title":"Mon robot drague 35 filles sur Tinder. (voici ce que j'ai appris...)","link":"https://www.youtube.com/watch?v=AY8uhQETv4w","pubDate":"2022-07-24T10:55:47.000Z","author":"Defend Intelligence","id":"yt:video:AY8uhQETv4w","isoDate":"2022-07-24T10:55:47.000Z"},{"title":"2 IA se disputent sur le Bitcoin et les NFT (+ explications à la fin)","link":"https://www.youtube.com/watch?v=Yq5NPJJFq8g","pubDate":"2022-07-03T09:00:12.000Z","author":"Defend Intelligence","id":"yt:video:Yq5NPJJFq8g","isoDate":"2022-07-03T09:00:12.000Z"},{"title":"Dalle 2 : Quels sont les métiers qui vont disparaître avec l'IA ?","link":"https://www.youtube.com/watch?v=yqX_Tx9v3SI","pubDate":"2022-06-26T09:57:41.000Z","author":"Defend Intelligence","id":"yt:video:yqX_Tx9v3SI","isoDate":"2022-06-26T09:57:41.000Z"},{"title":"Une Intelligence Artificielle de Google consciente ?","link":"https://www.youtube.com/watch?v=PsX1HQJJ_u4","pubDate":"2022-06-22T16:46:28.000Z","author":"Defend Intelligence","id":"yt:video:PsX1HQJJ_u4","isoDate":"2022-06-22T16:46:28.000Z"},{"title":"La plus grande ARNAQUEUSE de 2022","link":"https://www.youtube.com/watch?v=9hL5Zi1DUdU","pubDate":"2022-06-12T17:34:02.000Z","author":"Defend Intelligence","id":"yt:video:9hL5Zi1DUdU","isoDate":"2022-06-12T17:34:02.000Z"},{"title":"J’infiltre un réseau d’arnaqueurs.","link":"https://www.youtube.com/watch?v=yn9A7ud3eXo","pubDate":"2022-06-05T17:08:22.000Z","author":"Defend Intelligence","id":"yt:video:yn9A7ud3eXo","isoDate":"2022-06-05T17:08:22.000Z"},{"title":"La FIN du Cyber-harcèlement","link":"https://www.youtube.com/watch?v=EXDxYcPC9vk","pubDate":"2022-05-01T10:00:07.000Z","author":"Defend Intelligence","id":"yt:video:EXDxYcPC9vk","isoDate":"2022-05-01T10:00:07.000Z"},{"title":"10 raisons de ne PAS devenir Data Scientist.","link":"https://www.youtube.com/watch?v=jmECuuw28wI","pubDate":"2022-04-17T09:42:23.000Z","author":"Defend Intelligence","id":"yt:video:jmECuuw28wI","isoDate":"2022-04-17T09:42:23.000Z"},{"title":"Mon robot ATTIRE un Jaguar ?","link":"https://www.youtube.com/watch?v=cyYw-UgEK-A","pubDate":"2022-04-10T09:59:27.000Z","author":"Defend Intelligence","id":"yt:video:cyYw-UgEK-A","isoDate":"2022-04-10T09:59:27.000Z"},{"title":"Le Data Poisoning, c'est quoi ?","link":"https://www.youtube.com/watch?v=XvAbvbQ2LdY","pubDate":"2022-02-13T11:00:14.000Z","author":"Defend Intelligence","id":"yt:video:XvAbvbQ2LdY","isoDate":"2022-02-13T11:00:14.000Z"},{"title":"Reportage - Comment l’Intelligence Artificielle est au service de nos déchets nucléaires ?","link":"https://www.youtube.com/watch?v=uNpJ3vM9j5s","pubDate":"2022-01-23T11:41:00.000Z","author":"Defend Intelligence","id":"yt:video:uNpJ3vM9j5s","isoDate":"2022-01-23T11:41:00.000Z"},{"title":"Un jour dans la vie d'un DATA SCIENTIST (télétravail)","link":"https://www.youtube.com/watch?v=w1i8zc1B-Jw","pubDate":"2022-01-16T13:11:20.000Z","author":"Defend Intelligence","id":"yt:video:w1i8zc1B-Jw","isoDate":"2022-01-16T13:11:20.000Z"},{"title":"Ce que la vision de l'IA de Matrix nous apprend sur notre futur.","link":"https://www.youtube.com/watch?v=dqtPWWB7ypk","pubDate":"2021-12-17T17:01:02.000Z","author":"Defend Intelligence","id":"yt:video:dqtPWWB7ypk","isoDate":"2021-12-17T17:01:02.000Z"},{"title":"Le Machine Learning c’est quoi ?","link":"https://www.youtube.com/watch?v=RC7GTAKoFGA","pubDate":"2021-12-08T10:57:00.000Z","author":"Defend Intelligence","id":"yt:video:RC7GTAKoFGA","isoDate":"2021-12-08T10:57:00.000Z"}]